deskset/README.md
deskset/__init__.py
deskset/core/README.md
deskset/core/__init__.py
deskset/core/config.py
deskset/core/locale.py
deskset/core/log.py
deskset/core/root_path.py
deskset/core/standard.py
deskset/core/text_file.py
deskset/feature/README.md
deskset/feature/__init__.py
deskset/feature/current.py
deskset/feature/device/__init__.py
deskset/feature/device/abstract.py
deskset/feature/device/win32.py
deskset/feature/greet.py
deskset/feature/note/__init__.py
deskset/feature/note/obsidian/__init__.py
deskset/feature/note/obsidian/_check.py
deskset/feature/note/obsidian/conf/__init__.py
deskset/feature/note/obsidian/conf/conf_on_deskset.py
deskset/feature/note/obsidian/conf/conf_on_vault.py
deskset/feature/note/scheduler.py
deskset/feature/quick/__init__.py
deskset/feature/quick/_check.py
deskset/feature/quick/app.py
deskset/feature/quick/fileinfo.py
deskset/feature/quick/open.py
deskset/feature/search/__init__.py
deskset/feature/search/search.py
deskset/feature/wallpaper.py
deskset/main.py
deskset/router/__init__.py
deskset/router/api.py
deskset/router/cloud.py
deskset/router/current.py
deskset/router/debug.py
deskset/router/device.py
deskset/router/greet.py
deskset/router/note/__init__.py
deskset/router/note/obsidian/__init__.py
deskset/router/note/obsidian/_manager.py
deskset/router/note/obsidian/_noteapi.py
deskset/router/note/obsidian/_validate.py
deskset/router/note/obsidian/common.py
deskset/router/note/obsidian/diary.py
deskset/router/note/obsidian/profile.py
deskset/router/note/obsidian/search.py
deskset/router/note/obsidian/stats.py
deskset/router/note/scheduler.py
deskset/router/quick.py
deskset/router/unify/__init__.py
deskset/router/unify/access.py
deskset/router/unify/request.py
deskset/router/unify/response.py
deskset/router/weather.py
deskset-0.0.2a0.dist-info/LICENSE
deskset-0.0.2a0.dist-info/METADATA
deskset-0.0.2a0.dist-info/WHEEL
deskset-0.0.2a0.dist-info/RECORD
